MANIFEST.in
README.md
setup.py
AttachmentsExtractor/__init__.py
AttachmentsExtractor/__main__.py
AttachmentsExtractor/extractor.py
AttachmentsExtractor.egg-info/PKG-INFO
AttachmentsExtractor.egg-info/SOURCES.txt
AttachmentsExtractor.egg-info/dependency_links.txt
AttachmentsExtractor.egg-info/entry_points.txt
AttachmentsExtractor.egg-info/requires.txt
AttachmentsExtractor.egg-info/top_level.txt