Metadata-Version: 2.1
Name: AttachmentsExtractor
Version: 1.0.2
Summary: Extracts Embeded documents From Open XML documents. Such as excels, documents, presentations etc. .
Home-page: https://github.com/surajForDD/AttachmentsExtractor
Author: Suraj Kumar
Author-email: surajkm09@gmail.com
License: MIT
Platform: UNKNOWN
Classifier: License :: OSI Approved :: MIT License
Classifier: Programming Language :: Python :: 3
Classifier: Programming Language :: Python :: 3.7
